Metadata-Version: 1.1
Name: notes-cli
Version: 0.2
Summary: command line tool for your notes
Home-page: https://github.com/bigolu/notes-cli
Author: Olaolu Biggie Emmanuel
Author-email: hi@bigo.lu
License: MIT
Keywords: notes cli
Platform: UNKNOWN
Classifier: Development Status :: 3 - Alpha
Classifier: License :: OSI Approved :: MIT License
Classifier: Programming Language :: Python :: 3.5
Classifier: Topic :: Terminals
